{
    "prepare_queue": {
        "installed": [],
        "uninstalled": []
    },
    "config_munge": {
        "files": {}
    },
    "installed_plugins": {
        "cordova-plugin-whitelist": {
            "PACKAGE_NAME": "com.packtpub.phonegaphotshot.test"
        },
        "cordova-plugin-globalization": {
            "PACKAGE_NAME": "com.packtpub.phonegaphotshot.test"
        },
        "ionic-plugin-keyboard": {
            "PACKAGE_NAME": "com.packtpub.phonegaphotshot.test"
        },
        "cordova-plugin-file": {
            "PACKAGE_NAME": "com.packtpub.phonegaphotshot.test"
        }
    },
    "dependent_plugins": {
        "cordova-plugin-compat": {
            "PACKAGE_NAME": "com.packtpub.phonegaphotshot.test"
        }
    }
}